Metadata-Version: 2.1
Name: soundstretch
Version: 1.2
Summary: SoundStretch based on Paulstretch algorithm
Home-page: https://github.com/jbvolmer/soundstretch
Author: J. Volmer
Author-email: josephbvolmer@gmail.com
License: Public Domain
Platform: UNKNOWN
